mm_mamba/__init__.py
mm_mamba/block.py
mm_mamba/model.py
mmm_zeta-0.1.1.dist-info/LICENSE
mmm_zeta-0.1.1.dist-info/WHEEL
mmm_zeta-0.1.1.dist-info/METADATA
mmm_zeta-0.1.1.dist-info/RECORD
