Metadata-Version: 2.1
Name: mmm-zeta
Version: 0.1.1
Summary: MultiModalMamba - Pytorch
Home-page: https://github.com/kyegomez/MultiModalMamba
License: MIT
Keywords: artificial intelligence,deep learning,optimizers,Prompt Engineering
Author: Kye Gomez
Author-email: kye@apac.ai
Requires-Python: >=3.6,<4.0
Classifier: Development Status :: 4 - Beta
Classifier: Intended Audience :: Developers
Classifier: License :: OSI Approved :: MIT License
Classifier: Programming Language :: Python :: 3
Classifier: Programming Language :: Python :: 3.6
Classifier: Programming Language :: Python :: 3.7
Classifier: Programming Language :: Python :: 3.8
Classifier: Programming Language :: Python :: 3.9
Classifier: Programming Language :: Python :: 3.10
Classifier: Programming Language :: Python :: 3.11
Classifier: Programming Language :: Python :: 3.9
Classifier: Topic :: Scientific/Engineering :: Artificial Intelligence
Requires-Dist: einops
Requires-Dist: torch (==2.1.2)
Requires-Dist: zetascale (==1.4.0)
Project-URL: Documentation, https://github.com/kyegomez/MultiModalMamba
Project-URL: Repository, https://github.com/kyegomez/MultiModalMamba
